examples/template.py
examples/template_expander.py
streamlit_chat_handler/__init__.py
streamlit_chat_handler/_handler.py
streamlit_chat_handler/types.py
streamlit_chat_handler-0.1.4.dist-info/LICENSE
streamlit_chat_handler-0.1.4.dist-info/METADATA
streamlit_chat_handler-0.1.4.dist-info/WHEEL
streamlit_chat_handler-0.1.4.dist-info/top_level.txt
streamlit_chat_handler-0.1.4.dist-info/RECORD
