Metadata-Version: 2.1
Name: streamlit_chat_handler
Version: 0.1.4
Summary: ...
Author-email: Eduardo Messias de Morais <emdemor415@gmail.com>
Keywords: sample,setuptools,development
Requires-Python: >=3.10
License-File: LICENSE
Requires-Dist: streamlit ==1.33.0
Requires-Dist: streamlit-chat ==0.1.1
Requires-Dist: streamlit-extras ==0.4.2
Requires-Dist: streamlit-feedback ==0.1.3
Requires-Dist: pydantic ==2.7.0
Requires-Dist: loguru
Provides-Extra: lint
Requires-Dist: black ==23.7.0 ; extra == 'lint'
Requires-Dist: flake8 ==6.1.0 ; extra == 'lint'
Requires-Dist: Flake8-pyproject ==1.2.3 ; extra == 'lint'
Requires-Dist: mypy ==1.4.1 ; extra == 'lint'
Requires-Dist: bandit ==1.7.5 ; extra == 'lint'
Provides-Extra: test
Requires-Dist: pytest ==7.4.0 ; extra == 'test'
Requires-Dist: pytest-cov ==4.1.0 ; extra == 'test'
Requires-Dist: pytest-mock ==3.11.1 ; extra == 'test'
Requires-Dist: pytest-mypy ==0.10.3 ; extra == 'test'
